l0n0lacltester/__init__.py
l0n0lacltester/gen_cpu_call_code.py
l0n0lacltester/tiling_context.py
l0n0lacltester/utils.py
l0n0lacltester/workspace_files/CMakeLists.txt
l0n0lacltester/workspace_files/gitignore
l0n0lacltester/workspace_files/run.py
l0n0lacltester/workspace_files/run.sh
l0n0lacltester/workspace_files/tiling_context.cpp
l0n0lacltester/workspace_files/cmake/cpu_lib.cmake
l0n0lacltester/workspace_files/cmake/npu_lib.cmake
l0n0lacltester/workspace_files/include/AclEnv.h
l0n0lacltester/workspace_files/include/AclGmMemory.h
l0n0lacltester/workspace_files/include/AclMemory.h
l0n0lacltester/workspace_files/include/AclStream.h
l0n0lacltester/workspace_files/include/all.h
l0n0lacltester/workspace_files/include/data_utils.h
l0n0lacltester/workspace_files/include/tiling_context.h
l0n0lacltester/workspace_files/include/tiling_data_base.h
l0n0lacltester/workspace_files/include/tiling_data_desc.h
l0n0lacltester/workspace_files/include/tiling_data_kernel.h
l0n0lacltester/workspace_files/include/tiling_shape.h
l0n0lacltester/workspace_files/include/utils.h
l0n0lacltester-1.0.15.dist-info/LICENSE
l0n0lacltester-1.0.15.dist-info/METADATA
l0n0lacltester-1.0.15.dist-info/WHEEL
l0n0lacltester-1.0.15.dist-info/entry_points.txt
l0n0lacltester-1.0.15.dist-info/top_level.txt
l0n0lacltester-1.0.15.dist-info/RECORD
